{
  "level": [
    {
      "id": 1,
      "image": "image_1.png",
      "level": "1",
      "numberQuestion": "20",
      "numberQuestionDone": 0,
      "process": 0,
      "listQuestionLevel": [
        {
          "uid" : 1,
          "question": 1,
          "imageQuestion": "americamineiro.jpg",
          "name": "americamineiro",
          "isDone" : false,
          "levelDetail": "1"

        },
        {
          "uid" : 2,
          "question": 2,
          "imageQuestion": "athleticoparanaense.jpg",
          "name": "athleticoparanaense",
          "isDone" : false,
          "levelDetail": "1"
        },
        {
          "uid" : 3,
          "question": 3,
          "imageQuestion": "atleticomineiro.jpg",
          "name": "atleticomineiro",
          "isDone" : false,
          "levelDetail": "1"
        },
        {
          "uid" : 4,
          "question": 4,
          "imageQuestion": "bahia.jpg",
          "name": "bahia",
          "levelDetail": "1"
        },
        {
          "uid" : 5,
          "question": 5,
          "imageQuestion": "botafogo.jpg",
          "name": "botafogo",
          "isDone" : false,
          "levelDetail": "1"
        },
        {
          "uid" : 6,
          "question": 6,
          "imageQuestion": "corinthians.jpg",
          "name": "corinthians",
          "isDone" : false,
          "levelDetail": "1"
        },
        {
          "uid" : 7,
          "question": 7,
          "imageQuestion": "coritiba.jpg",
          "name": "coritiba",
          "isDone" : false,
          "levelDetail": "1"
        },
        {
          "uid" : 8,
          "question": 8,
          "imageQuestion": "cruzeiro.jpg",
          "name": "cruzeiro",
          "isDone" : false,
          "levelDetail": "1"
        },
        {
          "uid" : 9,
          "question": 9,
          "imageQuestion": "cuiaba.jpg",
          "name": "cuiaba",
          "isDone" : false,
          "levelDetail": "1"
        },
        {
          "uid" : 10,
          "question": 10,
          "imageQuestion": "flamengo.jpg",
          "name": "flamengo",
          "isDone" : false,
          "levelDetail": "1"
        },
        {
          "uid" : 11,
          "question": 11,
          "imageQuestion": "fluminense.jpg",
          "name": "fluminense",
          "isDone" : false,
          "levelDetail": "1"
        },
        {
          "uid" : 12,
          "question": 12,
          "imageQuestion": "fortaleza.jpg",
          "name": "fortaleza",
          "isDone" : false,
          "levelDetail": "1"
        },
        {
          "uid" : 13,
          "question": 13,
          "imageQuestion": "goias.jpg",
          "name": "goias",
          "isDone" : false,
          "levelDetail": "1"
        },
        {
          "uid" : 14,
          "question": 14,
          "imageQuestion": "grêmio.jpg",
          "name": "grêmio",
          "isDone" : false,
          "levelDetail": "1"
        },
        {
          "uid" : 15,
          "question": 15,
          "imageQuestion": "internacional.jpg",
          "name": "internacional",
          "isDone" : false,
          "levelDetail": "1"
        },
        {
          "uid" : 16,
          "question": 16,
          "imageQuestion": "palmeiras.jpg",
          "name": "palmeiras",
          "isDone" : false,
          "levelDetail": "1"
        },
        {
          "uid" : 17,
          "question": 17,
          "imageQuestion": "RB Bragantino.jpg",
          "name": "RB Bragantino",
          "isDone" : false,
          "levelDetail": "1"
        },
        {
          "uid" : 18,
          "question": 18,
          "imageQuestion": "santos.jpg",
          "name": "santos",
          "isDone" : false,
          "levelDetail": "1"
        },
        {
          "uid" : 19,
          "question": 19,
          "imageQuestion": "São Paulo.jpg",
          "name": "São Paulo",
          "isDone" : false,
          "levelDetail": "1"
        },
        {
          "uid" : 20,
          "question": 20,
          "imageQuestion": "Vasco.jpg",
          "name": "Vaseco",
          "isDone" : false,
          "levelDetail": "1"
        }
      ]
    },
    {
      "id": 2,
      "image": "image_2.png",
      "level": "2",
      "numberQuestion": "20",
      "numberQuestionDone": "0",
      "process": 0,
      "listQuestionLevel": [
        {
          "uid" : 21,
          "question": 1,
          "imageQuestion": "ABC.jpg",
          "name": "ABC",
          "isDone" : false,
          "levelDetail" : "2"
        },
        {
          "uid" : 22,
          "question": 2,
          "imageQuestion": "Atlético Goianiense.jpg",
          "name": "Atlético Goianiense",
          "isDone" : false,
          "levelDetail" : "2"
        },
        {
          "uid" : 23,
          "question": 3,
          "imageQuestion": "Avaí.jpg",
          "name": "Avaí",
          "isDone" : false,
          "levelDetail" : "2"
        },
        {
          "uid" : 24,
          "question": 4,
          "imageQuestion": "Botafogo SP.jpg",
          "name": "Botafogo SP",
          "isDone" : false,
          "levelDetail" : "2"
        },
        {
          "uid" : 25,
          "question": 5,
          "imageQuestion": "Ceará.jpg",
          "name": "Ceará",
          "isDone" : false,
          "levelDetail" : "2"
        },
        {
          "uid" : 26,
          "question": 6,
          "imageQuestion": "Chapecoense.jpg",
          "name": "Chapecoense.jpg",
          "isDone" : false,
          "levelDetail" : "2"
        },
        {
          "uid" : 27,
          "question": 7,
          "imageQuestion": "CRB.jpg",
          "name": "CRB",
          "isDone" : false,
          "levelDetail" : "2"
        },
        {
          "uid" : 28,
          "question": 8,
          "imageQuestion": "Criciúma.jpg",
          "name": "Criciúma",
          "isDone" : false,
          "levelDetail" : "2"
        },
        {
          "uid" : 29,
          "question": 9,
          "imageQuestion": "Guarani.jpg",
          "name": "Guarani",
          "isDone" : false,
          "levelDetail" : "2"
        },
        {
          "uid" : 30,
          "question": 10,
          "imageQuestion": "Ituano.jpg",
          "name": "Ituano",
          "isDone" : false,
          "levelDetail" : "2"
        },
        {
          "uid" : 31,
          "question": 11,
          "imageQuestion": "Juventude.jpg",
          "name": "Juventude",
          "isDone" : false,
          "levelDetail" : "2"
        },
        {
          "uid" : 32,
          "question": 12,
          "imageQuestion": "Londrina.jpg",
          "name": "Londrina",
          "isDone" : false,
          "levelDetail" : "2"
        },
        {
          "uid" : 33,
          "question": 13,
          "imageQuestion": "Mirassol.jpg",
          "name": "Mirassol",
          "isDone" : false,
          "levelDetail" : "2"
        },
        {
          "uid" : 34,
          "question": 14,
          "imageQuestion": "Novorizontino.jpg",
          "name": "Novorizontino",
          "isDone" : false,
          "levelDetail" : "2"
        },
        {
          "uid" : 35,
          "question": 15,
          "imageQuestion": "Ponte Preta.jpg",
          "name": "Ponte Preta",
          "isDone" : false,
          "levelDetail" : "2"
        },
        {
          "uid" : 36,
          "question": 16,
          "imageQuestion": "Recife.jpg",
          "name": "Recife",
          "isDone" : false,
          "levelDetail" : "2"
        },
        {
          "uid" : 37,
          "question": 17,
          "imageQuestion": "Sampaio Corrêa.jpg",
          "name": "Sampaio Corrêa.jpg",
          "isDone" : false,
          "levelDetail" : "2"
        },
        {
          "uid" : 38,
          "question": 18,
          "imageQuestion": "Tombense.jpg",
          "name": "Tombense",
          "isDone" : false,
          "levelDetail" : "2"
        },
        {
          "uid" : 39,
          "question": 19,
          "imageQuestion": "Vila Nova.jpg",
          "name": "Vila Nova",
          "isDone" : false,
          "levelDetail" : "2"
        },
        {
          "uid" : 40,
          "question": 20,
          "imageQuestion": "Vitória.jpg",
          "name": "Vitória",
          "isDone" : false,
          "levelDetail" : "2"
        }
      ]
    },
    {
      "id": 3,
      "image": "image_3.png",
      "level": "3",
      "numberQuestion": "20",
      "numberQuestionDone": "0",
      "process": 0,
      "listQuestionLevel": [
        {
          "uid" : 41,
          "question": 1,
          "imageQuestion": "Arsenal.jpg",
          "name": "Arsenal",
          "isDone" : false,
          "levelDetail" : "3"
        },
        {
          "uid" : 42,
          "question": 2,
          "imageQuestion": "Aston Villa.jpg",
          "name": "Aston Villa",
          "isDone" : false,
          "levelDetail" : "3"
        },
        {
          "uid" : 43,
          "question": 3,
          "imageQuestion": "Bournemouth.jpg",
          "name": "Bournemouth",
          "isDone" : false,
          "levelDetail" : "3"
        },
        {
          "uid" : 44,
          "question": 4,
          "imageQuestion": "Brentford.jpg",
          "name": "Brentford",
          "isDone" : false,
          "levelDetail" : "3"
        },
        {
          "uid" : 45,
          "question": 5,
          "imageQuestion": "Brighton.jpg",
          "name": "Brighton",
          "isDone" : false,
          "levelDetail" : "3"
        },
        {
          "uid" : 46,
          "question": 6,
          "imageQuestion": "Burnley.jpg",
          "name": "Burnley",
          "isDone" : false,
          "levelDetail" : "3"
        },
        {
          "uid" : 47,
          "question": 7,
          "imageQuestion": "Chelsea.jpg",
          "name": "Chelsea",
          "isDone" : false,
          "levelDetail" : "3"
        },
        {
          "uid" : 48,
          "question": 8,
          "imageQuestion": "Crystal Palace.jpg",
          "name": "Crystal Palace",
          "isDone" : false,
          "levelDetail" : "3"
        },
        {
          "uid" : 49,
          "question" : 9,
          "imageQuestion": "Everton.jpg",
          "name": "Everton",
          "isDone" : false,
          "levelDetail" : "3"
        },
        {
          "uid" : 50,
          "question": 10,
          "imageQuestion": "Fulham.jpg",
          "name": "Fulham",
          "isDone" : false,
          "levelDetail" : "3"
        },
        {
          "uid" : 51,
          "question": 11,
          "imageQuestion": "Liverpool.jpg",
          "name": "Liverpool",
          "isDone" : false,
          "levelDetail" : "3"
        },
        {
          "uid" : 52,
          "question": 12,
          "imageQuestion": "Luton Town.jpg",
          "name": "Luton Town",
          "isDone" : false,
          "levelDetail" : "3"
        },
        {
          "uid" : 53,
          "question": 13,
          "imageQuestion": "Manchester City.jpg",
          "name": "Manchester City",
          "isDone" : false,
          "levelDetail" : "3"
        },
        {
          "uid" : 54,
          "question": 14,
          "imageQuestion": "Manchester United.jpg",
          "name": "Manchester United",
          "isDone" : false,
          "levelDetail" : "3"
        },
        {
          "uid" : 55,
          "question": 15,
          "imageQuestion": "Newcastle United.jpg",
          "name": "Newcastle United",
          "isDone" : false,
          "levelDetail" : "3"
        },
        {
          "uid" : 56,
          "question": 16,
          "imageQuestion": "Nottingham Forest.jpg",
          "name": "Nottingham Forest",
          "isDone" : false,
          "levelDetail" : "3"
        },
        {
          "uid" : 57,
          "question": 17,
          "imageQuestion": "Sheffield United.jpg",
          "name": "Sheffield United",
          "isDone" : false,
          "levelDetail" : "3"
        },
        {
          "uid" : 58,
          "question": 18,
          "imageQuestion": "Tottenham Hotspur.jpg",
          "name": "Tottenham Hotspur",
          "isDone" : false,
          "levelDetail" : "3"
        },
        {
          "uid" : 59,
          "question": 19,
          "imageQuestion": "West Ham United.jpg",
          "name": "West Ham United",
          "isDone" : false,
          "levelDetail" : "3"
        },
        {
          "uid" : 60,
          "question": 20,
          "imageQuestion": "Wolverhampton.jpg",
          "name": "Wolverhampton",
          "isDone" : false,
          "levelDetail" : "3"
        }
      ]
    },
    {
      "id": 4,
      "image": "image_4.png",
      "level": "4",
      "numberQuestion": "20",
      "numberQuestionDone": "0",
      "process": 0,
      "listQuestionLevel": [
        {
          "uid" : 61,
          "question": 1,
          "imageQuestion": "Almería.jpg",
          "name": "Almería",
          "isDone" : false,
          "levelDetail" : "4"
        },
        {
          "uid" : 62,
          "question": 2,
          "imageQuestion": "Athletic Bilbao.jpg",
          "name": "Athletic Bilbao",
          "isDone" : false,
          "levelDetail" : "4"
        },
        {
          "uid" : 63,
          "question": 3,
          "imageQuestion": "Atlético Madrid.jpg",
          "name": "Atlético Madrid",
          "isDone" : false,
          "levelDetail" : "4"
        },
        {
          "uid" : 64,
          "question": 4,
          "imageQuestion": "Barcelona.jpg",
          "name": "Barcelona",
          "isDone" : false,
          "levelDetail" : "4"
        },
        {
          "uid" : 65,
          "question": 5,
          "imageQuestion": "Cádiz.jpg",
          "name": "Cádiz.jpg",
          "isDone" : false,
          "levelDetail" : "4"
        },
        {
          "uid" : 66,
          "question": 6,
          "imageQuestion": "Deportivo Alavés.jpg",
          "name": "Deportivo Alavés",
          "isDone" : false,
          "levelDetail" : "4"
        },
        {
          "uid" : 67,
          "question": 7,
          "imageQuestion": "Getafe.jpg",
          "name": "Getafe.jpg",
          "isDone" : false,
          "levelDetail" : "4"
        },
        {
          "uid" : 68,
          "question": 8,
          "imageQuestion": "Girona.jpg",
          "name": "Girona",
          "isDone" : false,
          "levelDetail" : "4"
        },
        {
          "uid" : 69,
          "question": 9,
          "imageQuestion": "Granada.jpg",
          "name": "Granada",
          "isDone" : false,
          "levelDetail" : "4"
        },
        {
          "uid" : 70,
          "question": 10,
          "imageQuestion": "Las Palmas.jpg",
          "name": "Las Palmas",
          "isDone" : false,
          "levelDetail" : "4"
        },
        {
          "uid" : 71,
          "question": 11,
          "imageQuestion": "Mallorca.jpg",
          "name": "Mallorca",
          "isDone" : false,
          "levelDetail" : "4"
        },
        {
          "uid" : 72,
          "question": 12,
          "imageQuestion": "Osasuna.jpg",
          "name": "Osasuna",
          "isDone" : false,
          "levelDetail" : "4"
        },
        {
          "uid" : 73,
          "question": 13,
          "imageQuestion": "Rayo Vallecano.jpg",
          "name": "Rayo Vallecano",
          "isDone" : false,
          "levelDetail" : "4"
        },
        {
          "uid" : 74,
          "question": 14,
          "imageQuestion": "Real Betis.jpg",
          "name": "Real Betis.jpg",
          "isDone" : false,
          "levelDetail" : "4"
        },
        {
          "uid" : 75,
          "question": 15,
          "imageQuestion": "Real Madrid.jpg",
          "name": "Real Madrid",
          "isDone" : false,
          "levelDetail" : "4"
        },
        {
          "uid" : 76,
          "question": 16,
          "imageQuestion": "Real Sociedad.jpg",
          "name": "Real Sociedad",
          "isDone" : false,
          "levelDetail" : "4"
        },
        {
          "uid" : 77,
          "question": 17,
          "imageQuestion": "Sevilla.jpg",
          "name": "Sevilla",
          "isDone" : false,
          "levelDetail" : "4"
        },
        {
          "uid" : 78,
          "question": 18,
          "imageQuestion": "Valencia.jpg",
          "name": "Valencia",
          "isDone" : false,
          "levelDetail" : "4"
        },
        {
          "uid" : 79,
          "question": 19,
          "imageQuestion": "Valencia.jpg",
          "name": "Valencia.jpg",
          "isDone" : false,
          "levelDetail" : "4"
        },
        {
          "uid" : 80,
          "question": 20,
          "imageQuestion": "Celta de Vigo.jpg",
          "name": "Celta de Vigo",
          "isDone" : false,
          "levelDetail" : "4"
        }
      ]
    },
    {
      "id": 5,
      "image": "image_5.png",
      "level": "5",
      "numberQuestion": "20",
      "numberQuestionDone": "0",
      "process": 0,
      "listQuestionLevel": [
        {
          "uid" : 81,
          "question": 1,
          "imageQuestion": "Augsburg.jpg",
          "name": "Augsburg",
          "isDone" : false,
          "levelDetail" : "5"
        },
        {
          "uid" : 82,
          "question": 2,
          "imageQuestion": "Bayer Leverkusen.jpg",
          "name": "Bayer Leverkusen",
          "isDone" : false,
          "levelDetail" : "5"
        },
        {
          "uid" : 83,
          "question": 3,
          "imageQuestion": "Bayern München.jpg",
          "name": "Bayern München",
          "isDone" : false,
          "levelDetail" : "5"
        },
        {
          "uid" : 84,
          "question": 4,
          "imageQuestion": "Bochum.jpg",
          "name": "Bochum",
          "isDone" : false,
          "levelDetail" : "5"
        },
        {
          "uid" : 85,
          "question": 5,
          "imageQuestion": "Borussia Dortmund.jpg",
          "name": "Borussia Dortmund",
          "isDone" : false,
          "levelDetail" : "5"
        },
        {
          "uid" : 86,
          "question": 6,
          "imageQuestion": "Borussia Mönchengladbach.jpg",
          "name": "Borussia Mönchengladbach",
          "isDone" : false,
          "levelDetail" : "5"
        },
        {
          "uid" : 87,
          "question": 7,
          "imageQuestion": "Darmstadt.jpg",
          "name": "Darmstadt",
          "isDone" : false,
          "levelDetail" : "5"
        },
        {
          "uid" : 88,
          "question": 8,
          "imageQuestion": "Eintracht Frankfurt.jpg",
          "name": "Eintracht Frankfurt",
          "isDone" : false,
          "levelDetail" : "5"
        },
        {
          "uid" : 89,
          "question": 9,
          "imageQuestion": "Freiburg.jpg",
          "name": "Freiburg",
          "isDone" : false,
          "levelDetail" : "5"
        },
        {
          "uid" : 90,
          "question": 10,
          "imageQuestion": "Heidenheim.jpg",
          "name": "Heidenheim",
          "isDone" : false,
          "levelDetail" : "5"
        },
        {
          "uid" : 91,
          "question": 11,
          "imageQuestion": "Hoffenheim.jpg",
          "name": "Hoffenheim.jpg",
          "isDone" : false,
          "levelDetail" : "5"
        },
        {
          "uid" : 92,
          "question": 12,
          "imageQuestion": "Köln.jpg",
          "name": "Köln",
          "isDone" : false,
          "levelDetail" : "5"
        },
        {
          "uid" : 93,
          "question": 13,
          "imageQuestion": "Mainz 05.jpg",
          "name": "Mainz 05",
          "isDone" : false,
          "levelDetail" : "5"
        },
        {
          "uid" : 94,
          "question": 14,
          "imageQuestion": "RB Leipzig.jpg",
          "name": "RB Leipzig",
          "isDone" : false,
          "levelDetail" : "5"
        },
        {
          "uid" : 95,
          "question": 15,
          "imageQuestion": "Union Berlin.jpg",
          "name": "Union Berlin",
          "isDone" : false,
          "levelDetail" : "5"
        },
        {
          "uid" : 96,
          "question": 16,
          "imageQuestion": "VfB Stuttgart.jpg",
          "name": "VfB Stuttgart",
          "isDone" : false,
          "levelDetail" : "5"
        },
        {
          "uid" : 97,
          "question": 17,
          "imageQuestion": "Werder Bremen.jpg",
          "name": "Werder Bremen",
          "isDone" : false,
          "levelDetail" : "5"
        },
        {
          "uid" : 98,
          "question": 18,
          "imageQuestion": "Wolfsburg.jpg",
          "name": "Wolfsburg",
          "isDone" : false,
          "levelDetail" : "5"
        }
      ]
    },
    {
      "id": 6,
      "image": "image_6.png",
      "level": "6",
      "numberQuestion": "20",
      "numberQuestionDone": "0",
      "process": 0,
      "listQuestionLevel": [
        {
          "uid" : 101,
          "question": 1,
          "imageQuestion": "Atalanta.jpg",
          "name": "Atalanta",
          "isDone" : false,
          "levelDetail" : "6"
        },
        {
          "uid" : 102,
          "question": 2,
          "imageQuestion": "Bologna.jpg",
          "name": "Bologna",
          "isDone" : false,
          "levelDetail" : "6"
        },
        {
          "uid" : 103,
          "question": 3,
          "imageQuestion": "Cagliari.jpg",
          "name": "Cagliari",
          "isDone" : false,
          "levelDetail" : "6"
        },
        {
          "uid" : 104,
          "question": 4,
          "imageQuestion": "Empoli.jpg",
          "name": "Empoli",
          "isDone" : false,
          "levelDetail" : "6"
        },
        {
          "uid" : 105,
          "question": 5,
          "imageQuestion": "Fiorentina.jpg",
          "name": "Fiorentina",
          "isDone" : false,
          "levelDetail" : "6"
        },
        {
          "uid" : 106,
          "question": 6,
          "imageQuestion": "Frosinone.jpg",
          "name": "Frosinone",
          "isDone" : false,
          "levelDetail" : "6"
        },
        {
          "uid" : 107,
          "question": 7,
          "imageQuestion": "Genoa.jpg",
          "name": "Genoa",
          "isDone" : false,
          "levelDetail" : "6"
        },
        {
          "uid" : 108,
          "question": 8,
          "imageQuestion": "Internazionale.jpg",
          "name": "Internazionale.jpg",
          "isDone" : false,
          "levelDetail" : "6"
        },
        {
          "uid" : 109,
          "question": 9,
          "imageQuestion": "Juventus.jpg",
          "name": "Juventus.jpg",
          "isDone" : false,
          "levelDetail" : "6"
        },
        {
          "uid" : 110,
          "question": 10,
          "imageQuestion": "Lazio.jpg",
          "name": "Lazio",
          "isDone" : false,
          "levelDetail" : "6"
        },
        {
          "uid" : 111,
          "question": 11,
          "imageQuestion": "Lecce.jpg",
          "name": "Lecce",
          "isDone" : false,
          "levelDetail" : "6"
        },
        {
          "uid" : 112,
          "question": 12,
          "imageQuestion": "Milan.jpg",
          "name": "Milan",
          "isDone" : false,
          "levelDetail" : "6"
        },
        {
          "uid" : 113,
          "question": 13,
          "imageQuestion": "Monza.jpg",
          "name": "Monza",
          "isDone" : false,
          "levelDetail" : "6"
        },
        {
          "uid" : 114,
          "question": 14,
          "imageQuestion": "Napoli.jpg",
          "name": "Napoli",
          "isDone" : false,
          "levelDetail" : "6"
        },
        {
          "uid" : 115,
          "question": 15,
          "imageQuestion": "Roma.jpg",
          "name": "Roma",
          "isDone" : false,
          "levelDetail" : "6"
        },
        {
          "uid" : 116,
          "question": 16,
          "imageQuestion": "Salernitana.jpg",
          "name": "Salernitana",
          "isDone" : false,
          "levelDetail" : "6"
        },
        {
          "uid" : 117,
          "question": 17,
          "imageQuestion": "Sassuolo.jpg",
          "name": "Sassuolo",
          "isDone" : false,
          "levelDetail" : "6"
        },
        {
          "uid" : 118,
          "question": 18,
          "imageQuestion": "Torino.jpg",
          "name": "Torino",
          "isDone" : false,
          "levelDetail" : "6"
        },
        {
          "uid" : 119,
          "question": 19,
          "imageQuestion": "Udinese.jpg",
          "name": "Udinese",
          "isDone" : false,
          "levelDetail" : "6"
        },
        {
          "uid" : 120,
          "question": 20,
          "imageQuestion": "Verona.jpg",
          "name": "Verona",
          "isDone" : false,
          "levelDetail" : "6"
        }
      ]
    },
    {
      "id": 7,
      "image": "image_7.png",
      "level": "7",
      "numberQuestion": "20",
      "numberQuestionDone": "0",
      "process": 0,
      "listQuestionLevel": [
        {
          "uid" : 121,
          "question": 1,
          "imageQuestion": "Le Havre.jpg",
          "name": "Le Havre",
          "isDone" : false,
          "levelDetail" : "7"
        },
        {
          "uid" : 122,
          "question": 2,
          "imageQuestion": "Lens.jpg",
          "name": "Lens",
          "isDone" : false,
          "levelDetail" : "7"
        },
        {
          "uid" : 123,
          "question": 3,
          "imageQuestion": "Lille OSC.jpg",
          "name": "Lille OSC.jpg",
          "isDone" : false,
          "levelDetail" : "7"
        },
        {
          "uid" : 124,
          "question": 4,
          "imageQuestion": "Lorient.jpg",
          "name": "Lorient",
          "isDone" : false,
          "levelDetail" : "7"
        },
        {
          "uid" : 125,
          "question": 5,
          "imageQuestion": "Metz.jpg",
          "name": "Metz",
          "isDone" : false,
          "levelDetail" : "7"
        },
        {
          "uid" : 126,
          "question": 6,
          "imageQuestion": "Monaco.jpg",
          "name": "Monaco",
          "isDone" : false,
          "levelDetail" : "7"
        },
        {
          "uid" : 127,
          "question": 7,
          "imageQuestion": "Montpellier.jpg",
          "name": "Montpellier",
          "isDone" : false,
          "levelDetail" : "7"
        },
        {
          "uid" : 128,
          "question": 8,
          "imageQuestion": "Nantes.jpg",
          "name": "Nantes",
          "isDone" : false,
          "levelDetail" : "7"
        },
        {
          "uid" : 129,
          "question": 9,
          "imageQuestion": "Nice.jpg",
          "name": "Nice",
          "isDone" : false,
          "levelDetail" : "7"
        },
        {
          "uid" : 130,
          "question": 10,
          "imageQuestion": "Olympique Lyonnais.jpg",
          "name": "Olympique Lyonnais",
          "isDone" : false,
          "levelDetail" : "7"
        },
        {
          "uid" : 131,
          "question": 11,
          "imageQuestion": "Olympique Marseille.jpg",
          "name": "Olympique Marseille",
          "isDone" : false,
          "levelDetail" : "7"
        },
        {
          "uid" : 132,
          "question": 12,
          "imageQuestion": "PSG.jpg",
          "name": "PSG",
          "isDone" : false,
          "levelDetail" : "7"
        },
        {
          "uid" : 133,
          "question": 13,
          "imageQuestion": "Racing.jpg",
          "name": "Racing",
          "isDone" : false,
          "levelDetail" : "7"
        },
        {
          "uid" : 134,
          "question": 14,
          "imageQuestion": "Stade Brestois.jpg",
          "name": "Stade Brestois",
          "isDone" : false,
          "levelDetail" : "7"
        },
        {
          "uid" : 135,
          "question": 15,
          "imageQuestion": "Stade de Reims.jpg",
          "name": "Stade de Reims",
          "isDone" : false,
          "levelDetail" : "7"
        },
        {
          "uid" : 136,
          "question": 16,
          "imageQuestion": "Stade Rennais.jpg",
          "name": "Stade Rennais",
          "isDone" : false,
          "levelDetail" : "7"
        },
        {
          "uid" : 137,
          "question": 17,
          "imageQuestion": "Toulouse.jpg",
          "name": "Toulouse",
          "isDone" : false,
          "levelDetail" : "7"
        }
      ]
    },
    {
      "id": 8,
      "image": "image_8.png",
      "level": "8",
      "numberQuestion": "20",
      "numberQuestionDone": "0",
      "process": 0,
      "listQuestionLevel": [
        {
          "uid" : 141,
          "question": 1,
          "imageQuestion": "Argentina.jpg",
          "name": "Argentina",
          "isDone" : false,
          "levelDetail" : "8"
        },
        {
          "uid" : 142,
          "question": 2,
          "imageQuestion": "Belgium.jpg",
          "name": "Belgium",
          "isDone" : false,
          "levelDetail" : "8"
        },
        {
          "uid" : 143,
          "question": 3,
          "imageQuestion": "Brasil.jpg",
          "name": "Brasil",
          "isDone" : false,
          "levelDetail" : "8"
        },
        {
          "uid" : 144,
          "question": 4,
          "imageQuestion": "Colombia.jpg",
          "name": "Colombia",
          "isDone" : false,
          "levelDetail" : "8"
        },
        {
          "uid" : 145,
          "question": 5,
          "imageQuestion": "Croatia.jpg",
          "name": "Croatia",
          "isDone" : false,
          "levelDetail" : "8"
        },
        {
          "uid" : 146,
          "question": 6,
          "imageQuestion": "Denmark.jpg",
          "name": "Denmark",
          "isDone" : false,
          "levelDetail" : "8"
        },
        {
          "uid" : 147,
          "question": 7,
          "imageQuestion": "England.jpg",
          "name": "England",
          "isDone" : false,
          "levelDetail" : "8"
        },
        {
          "uid" : 148,
          "question": 8,
          "imageQuestion": "France.jpg",
          "name": "France",
          "isDone" : false,
          "levelDetail" : "8"
        },
        {
          "uid" : 149,
          "question": 9,
          "imageQuestion": "Germany.jpg",
          "name": "Germany.jpg",
          "isDone" : false,
          "levelDetail" : "8"
        },
        {
          "uid" : 150,
          "question": 10,
          "imageQuestion": "Italy.jpg",
          "name": "Italy",
          "isDone" : false,
          "levelDetail" : "8"
        },
        {
          "uid" : 151,
          "question": 11,
          "imageQuestion": "Japan.jpg",
          "name": "Japan",
          "isDone" : false,
          "levelDetail" : "8"
        },
        {
          "uid" : 152,
          "question": 12,
          "imageQuestion": "Morocco.jpg",
          "name": "Morocco",
          "isDone" : false,
          "levelDetail" : "8"
        },
        {
          "uid" : 153,
          "question": 13,
          "imageQuestion": "México.jpg",
          "name": "México",
          "isDone" : false,
          "levelDetail" : "8"
        },
        {
          "uid" : 154,
          "question": 14,
          "imageQuestion": "Netherlands.jpg",
          "name": "Netherlands",
          "isDone" : false,
          "levelDetail" : "8"
        },
        {
          "uid" : 155,
          "question": 15,
          "imageQuestion": "Portugal.jpg",
          "name": "Portugal",
          "isDone" : false,
          "levelDetail" : "8"
        },
        {
          "uid" : 156,
          "question": 16,
          "imageQuestion": "Senegal.jpg",
          "name": "Senegal",
          "isDone" : false,
          "levelDetail" : "8"
        },
        {
          "uid" : 157,
          "question": 17,
          "imageQuestion": "Spain.jpg",
          "name": "Spain",
          "isDone" : false,
          "levelDetail" : "8"
        },
        {
          "uid" : 158,
          "question": 18,
          "imageQuestion": "Switzerland.jpg",
          "name": "Switzerland",
          "isDone" : false,
          "levelDetail" : "8"
        },
        {
          "uid" : 159,
          "question": 19,
          "imageQuestion": "United States.jpg",
          "name": "United States",
          "isDone" : false,
          "levelDetail" : "8"
        },
        {
          "uid" : 160,
          "question": 20,
          "imageQuestion": "Uruguai.jpg",
          "name": "Uruguai",
          "isDone" : false,
          "levelDetail" : "8"
        }
      ]
    }
  ]
}